samsung_galaxy_store/__init__.py
samsung_galaxy_store/cli.py
samsung_galaxy_store/models.py
samsung_galaxy_store/store.py
samsung_galaxy_store-0.1.10.dist-info/entry_points.txt
samsung_galaxy_store-0.1.10.dist-info/LICENSE
samsung_galaxy_store-0.1.10.dist-info/WHEEL
samsung_galaxy_store-0.1.10.dist-info/METADATA
samsung_galaxy_store-0.1.10.dist-info/RECORD
