Metadata-Version: 2.1
Name: samsung-galaxy-store
Version: 0.1.10
Summary: Samsung Galaxy Store analysis tools
Home-page: https://github.com/minormending/samsung-galaxy-store
License: MIT
Keywords: samsung,galaxy,appstore
Author: Kevin Ramdath
Author-email: krpent@gmail.com
Requires-Python: >=3.10,<4.0
Classifier: License :: OSI Approved :: MIT License
Classifier: Programming Language :: Python :: 3
Classifier: Programming Language :: Python :: 3.10
Requires-Dist: requests (>=2.27.1,<3.0.0)
Project-URL: Repository, https://github.com/minormending/samsung-galaxy-store
